{
	"133658139": {
		"money": 250,
		"dust": {
			"White": 0,
			"Red": 0,
			"Yellow": 0,
			"Blue": 0,
			"Purple": 0,
			"Black": 0
		},
		"armor": [],
		"weapon": [],
		"misc": [],
		"items": [
			{
				"id": 144,
				"name": "растворитель лунной призмы",
				"img": "photo133658139_457419854_eb2114808ba587f887",
				"description": " [ расходник]\n   \n  Способности: \n  После применения увеличивает базовую атаку на 120 единиц на 5 раундов. (эффекты не складываются; после использования аналогичного зелья, эффект от предыдущего отменяется и заменяется эффектом другого расходника.)\n  \n   Для применения необходимо потратить Бонусное действие.",
				"type": 4
			},
			{
				"id": 145,
				"name": "зелье регенерации",
				"img": "photo133658139_457419855_9f90142f6abbab8d8d",
				"description": " [ расходник ] \n   \n  Способности: \n  [Регенерация] – моментально восстанавливает 25% ХП после применения и в течение 3-х раундов восстанавливает по 200 единиц здоровья. (Невозможно накладывать эффект друг на друга с помощью аналогичных расходников) \n   \n  Эффект длится 3 раунда.\n  \n  Для применения необходимо потратить Бонусное действие.",
				"type": 4
			}
		],
		"safe": [],
		"safeAvailable": false
	},
	"334913416": {
		"money": 400,
		"dust": {
			"White": 0,
			"Red": 0,
			"Yellow": 0,
			"Blue": 0,
			"Purple": 0,
			"Black": 0
		},
		"armor": [
			137
		],
		"weapon": [],
		"misc": [],
		"items": [
			{
				"id": 137,
				"name": "носки",
				"img": "",
				"description": "",
				"type": 2
			}
		],
		"safe": [],
		"safeAvailable": true
	},
	"376582792": {
		"money": 92,
		"dust": {
			"White": 1,
			"Red": 0,
			"Yellow": 1,
			"Blue": 0,
			"Purple": 2,
			"Black": 0
		},
		"armor": [],
		"weapon": [],
		"misc": [],
		"items": [],
		"safe": [],
		"safeAvailable": false
	},
	"454968461": {
		"money": 469,
		"dust": {
			"White": 5,
			"Red": 0,
			"Yellow": 1,
			"Blue": 3,
			"Purple": 2,
			"Black": 1
		},
		"armor": [],
		"weapon": [],
		"misc": [],
		"items": [
			{
				"id": 126,
				"name": "Опал причудливой формы",
				"img": "photo559144282_457250537_11dc7dd57d29641b98",
				"description": "\n[ Небольшой оберег на случай битвы ] \n \n[ Брелок ] \n \nСпособность: \n[ Талисман защиты ] - Урон от первой атаки за раунд по владельцу понижается на 80% (раз за раунд).",
				"type": 3
			},
			{
				"id": 136,
				"name": "Зелье регенерации",
				"img": "photo559144282_457250583_e1a0675d4f86254a08",
				"description": "[ расходник ] \n \nСпособности: \n[Регенерация] – моментально восстанавливает 25% ХП после применения и в течение 3-х раундов восстанавливает по 200 единиц здоровья. (Невозможно накладывать эффект друг на друга с помощью аналогичных расходников) \n \nЭффект длится 3 раунда. \n \nДля применения необходимо потратить Бонусное действие.",
				"type": 4
			}
		],
		"safe": [],
		"safeAvailable": false
	},
	"477367787": {
		"money": 1136,
		"dust": {
			"White": 7,
			"Red": 3,
			"Yellow": 6,
			"Blue": 8,
			"Purple": 5,
			"Black": 4
		},
		"armor": [],
		"weapon": [],
		"misc": [],
		"items": [
			{
				"id": 122,
				"name": "Ледяной палаш",
				"img": "photo559144282_457250529_48e347713598649546",
				"description": "[ От него буквально исходит мертвый холод... ] \n \n[ Оружие ] \n \nУрон: +60 (Физ.) \n \nСпособности: \n \n[ Обморожение ] - Каждый удар наносит дополнительно 50% магического урона. Этот урон проходит как дополнительная атака. \n \n{ Замах } - Потребует больших усилий, но взамен вы нанесете урон сразу трем противникам на выбор. Расходует 30% выносливости (вместо 10%) исходя из вашего урона. Кд 2 раунда.",
				"type": 1
			},
			{
				"id": 123,
				"name": "Кристалл сосредоточения",
				"img": "photo559144282_457250530_1bf35a30121dd770f7",
				"description": "[ Увеличивает урон на близком расстоянии ] \n \n[ Брелок ] \n \nСпособность: \n[ Сосредоточенность ] - Урон по противнику, что ходит до вас или после на 1 деление (или более до ближайшего), увеличивается на 25% (+25% за предмет)",
				"type": 3
			},
			{
				"id": 124,
				"name": "Плюшевая моль",
				"img": "photo559144282_457250531_2c7e164a0d6b4d3035",
				"description": "[ Вид этой плюшевой куклы навивает вам воспоминания... ] \n \n[ Брелок ] \n \nСпособности: \n[ Тяжелые времена ] - 15% шанс полностью заблокировать атаку",
				"type": 3
			},
			{
				"id": 138,
				"name": "Доблесть Махаматры",
				"img": "photo477367787_457249011_bef6895243317eb197",
				"description": "[ Доблесть Махаматры ] \n \n[ Броня ] \n \n[ Броня: +270 ] \n[ Рег. вын.: +4 ] \n \nСпособности: \n[ Стойкость ] – Ношение брони увеличивает максимальную Выносливость на 5% от вашего макс. ХП, а также при целостности брони ниже ½ повышает сопротивление к любому типу урона (кроме Коррозии) у носителя на 15%.",
				"type": 2
			},
			{
				"id": 139,
				"name": "Хамелеон",
				"img": "photo477367787_457249015_bfa0f2290061db29e0",
				"description": "Способности: \n[ Дуновение ветра I ] – после использования отменяется Невидимость у врага и вам становиться доступна позиция врага для успешной атаки. \n \n[ Дуновение ветра II ] – отменяет эффект сокрытия позиции хода (не только для врага, но и вас). \n \nДлительность эффектов 2 раунда.\n\nДля применения необходимо потратить Бонусное действие.",
				"type": 4
			},
			{
				"id": 140,
				"name": "Растворитель лунной призмы",
				"img": "photo477367787_457249018_9e09126d27e7f25784",
				"description": "\nСпособности: \nПосле применения увеличивает базовую атаку на 120 единиц на 5 раундов. (эффекты не складываются; после использования аналогичного зелья, эффект от предыдущего отменяется и заменяется эффектом другого расходника.)\n\n Для применения необходимо потратить Бонусное действие.",
				"type": 4
			},
			{
				"id": 141,
				"name": "Зелье регенерации",
				"img": "photo477367787_457249019_354cf8245af91a9ca1",
				"description": "\nСпособности: \n[Регенерация] – моментально восстанавливает 25% ХП после применения и в течение 3-х раундов восстанавливает по 200 единиц здоровья. (Невозможно накладывать эффект друг на друга с помощью аналогичных расходников) \n \nЭффект длится 3 раунда.\n\nДля применения необходимо потратить Бонусное действие.",
				"type": 4
			}
		],
		"safe": [],
		"safeAvailable": false
	},
	"499576316": {
		"money": 195,
		"dust": {
			"White": 0,
			"Red": 0,
			"Yellow": 2,
			"Blue": 1,
			"Purple": 3,
			"Black": 4
		},
		"armor": [],
		"weapon": [],
		"misc": [],
		"items": [],
		"safe": [],
		"safeAvailable": false
	},
	"521835920": {
		"money": 958,
		"dust": {
			"White": 28,
			"Red": 32,
			"Yellow": 23,
			"Blue": 20,
			"Purple": 18,
			"Black": 30
		},
		"armor": [],
		"weapon": [],
		"misc": [],
		"items": [
			{
				"id": 135,
				"name": "Легкий доспех",
				"img": "photo559144282_457250579_e7390aca821f341f61",
				"description": "[ Броня ] \n \n[ Броня: +100 ] \n[ ХП: +50 ] \n \nСпособности: \n[ Лёгкая броня ] – Ношение брони увеличивает вашу инициативу на 10. При использовании Бонусного Действия есть ¼ шанс что ваша следующая атака будет эффективнее на 30% на 1 раунд (не складывается).",
				"type": 2
			},
			{
				"id": 142,
				"name": "Рельсотрон",
				"img": "photo521835920_457242674_bfd16380e8ee835bf2",
				"description": "Урон: 315 (лазер) \nВост. энергии: +5 \n \nСпособности: \n[ Полностью заряжен ] – добавляет статистику Заряд, а также на старте даëт 3 заряда, всего может быть 6 зарядов. Заряды накапливаются за время нахождения на побитвы без затрат Энергии, тоесть с максимальным еë значением (Выносливость, если вы не Дроид): { 1 раунд с макс. Энергией =1 Заряд, каждый следующий раунд с максимальной энергией +2 Заряда. } \n \n[ Разрушительный концентрированный поток фотонов ] – при накоплении 6/6 Зарядов вам даётся возможность за Бонусное Действие полностью разрядить (потратить 6 энергии) Рельсотрон, поражая одновременно до 4-х целей в порядке хода (либо вверх по списку, либо вниз), нанося 200% лазерного урона. (не считается массовым уроном)",
				"type": 1
			},
			{
				"id": 143,
				"name": "Ветвь Ивы",
				"img": "photo559144282_457250627_8d1a946707786d197a",
				"description": "[ Усиление брони ] \nБроня: +65 \n \n[ Брелок ] \n \nСпособности: \n[ Оберег ] – увеличивает сопротивление к любому виду урона (кроме чистого) на 15%",
				"type": 3
			},
			{
				"id": 157,
				"name": "[ Кристалл сосредоточения ]",
				"img": "",
				"description": " \n[ Увеличивает урон на близком расстоянии ] \n \n[ Брелок ] \n \nСпособность: \n[ Сосредоточенность ] - Урон по противнику, что ходит до вас или после на 1 деление (или более до ближайшего), увеличивается на 25% (+25% за предмет)",
				"type": 3
			},
			{
				"id": 158,
				"name": "[ Плюшевая моль ]",
				"img": "",
				"description": " \n[ Вид этой плюшевой куклы навивает вам воспоминания... ] \n \n[ Брелок ] \n \nСпособности: \n[ Тяжелые времена ] - 15% шанс полностью заблокировать атаку",
				"type": 3
			}
		],
		"safe": [],
		"safeAvailable": false
	},
	"557009179": {
		"money": 1151,
		"dust": {
			"White": 1,
			"Red": 9,
			"Yellow": 17,
			"Blue": 15,
			"Purple": 11,
			"Black": 10
		},
		"armor": [],
		"weapon": [],
		"misc": [],
		"items": [
			{
				"id": 154,
				"name": "доспех",
				"img": "photo559144282_457250698_bba414628cba4a3fbc",
				"description": "[ Броня ] \n \n[ Броня: +100 ] \n[ ХП: +50 ] \n \nСпособности: \n[ Лёгкая броня ] – Ношение брони увеличивает вашу инициативу на 10. При использовании Бонусного Действия есть ¼ шанс что ваша следующая атака будет эффективнее на 30% на 1 раунд (не складывается).",
				"type": 2
			},
			{
				"id": 156,
				"name": "Ветвь Ивы",
				"img": "",
				"description": "[ Усиление брони ] \nБроня: +65 \nСпособности: \n[ Оберег ] – увеличивает сопротивление к любому виду урона (кроме чистого) на 15%",
				"type": 3
			}
		],
		"safe": [],
		"safeAvailable": false
	},
	"559144282": {
		"money": 237,
		"dust": {
			"White": 1007,
			"Red": 2,
			"Yellow": 15,
			"Blue": 5,
			"Purple": 10,
			"Black": 4
		},
		"armor": [],
		"weapon": [
			159
		],
		"misc": [],
		"items": [
			{
				"id": 151,
				"name": "Доблесть Махаматры",
				"img": "photo559144282_457250692_17b7023f9c670393ca",
				"description": "[ Броня ] \n \n[ Броня: +270 ] \n[ Рег. вын.: +4 ] \n \nСпособности: \n[ Стойкость ] – Ношение брони увеличивает максимальную Выносливость на 5% от вашего макс. ХП, а также при целостности брони ниже ½ повышает сопротивление к любому типу урона (кроме Коррозии) у носителя на 15%.",
				"type": 2
			},
			{
				"id": 153,
				"name": "Зелье алой Ведьмы",
				"img": "photo559144282_457250697_7ca3342df34400e4df",
				"description": "[ Расходник ] \n \nСпособности: \n[ Пиро инфузия ] – ваш текущий тип атаки меняется, вы получаете тип атки Огонь, а также повышается урон от огня на 75%; при атаке на врага накладывается статус [ Горение ] на 3 раунда. \n \n[ Горение ] - Существо с данным статусом теряет 25% (от урона наложившего статус) ХП (Брони в случае Дроидов) каждый раунд до конца действия. \n \nДействие эффекта длится 3 раунда, эффекты не складывается посредством нескольких атак, Длительность статуса [ горение ] не сбрасывается; эффекты не суммируются посредством использования аналогичных зелий. \n \nДля применения необходимо потратить Бонусное действие.",
				"type": 4
			},
			{
				"id": 155,
				"name": "Доблесть Махаматры",
				"img": "photo559144282_457250703_9197ec3ba863fb1bf6",
				"description": "[ Броня ] \n \n[ Броня: +270 ] \n[ Рег. вын.: +4 ] \n \nСпособности: \n[ Стойкость ] – Ношение брони увеличивает максимальную Выносливость на 5% от вашего макс. ХП, а также при целостности брони ниже ½ повышает сопротивление к любому типу урона (кроме Коррозии) у носителя на 15%.",
				"type": 2
			},
			{
				"id": 159,
				"name": "пиво",
				"img": "",
				"description": "",
				"type": 1
			},
			{
				"id": 160,
				"name": "пиво",
				"img": "",
				"description": "",
				"type": 1
			},
			{
				"id": 161,
				"name": "пиво",
				"img": "",
				"description": "",
				"type": 1
			},
			{
				"id": 162,
				"name": "пиво",
				"img": "",
				"description": "",
				"type": 1
			},
			{
				"id": 163,
				"name": "пиво",
				"img": "",
				"description": "",
				"type": 1
			},
			{
				"id": 164,
				"name": "пиво",
				"img": "",
				"description": "",
				"type": 1
			},
			{
				"id": 165,
				"name": "пиво",
				"img": "",
				"description": "",
				"type": 1
			},
			{
				"id": 166,
				"name": "пиво",
				"img": "",
				"description": "",
				"type": 1
			},
			{
				"id": 167,
				"name": "пиво",
				"img": "",
				"description": "",
				"type": 1
			},
			{
				"id": 168,
				"name": "пиво",
				"img": "",
				"description": "",
				"type": 1
			},
			{
				"id": 169,
				"name": "пиво",
				"img": "",
				"description": "",
				"type": 1
			},
			{
				"id": 170,
				"name": "пиво",
				"img": "",
				"description": "",
				"type": 1
			}
		],
		"safe": [],
		"safeAvailable": false
	},
	"-214424423": {
		"money": 0,
		"dust": {
			"White": 0,
			"Red": 0,
			"Yellow": 0,
			"Blue": 0,
			"Purple": 0,
			"Black": 0
		},
		"armor": [],
		"weapon": [],
		"misc": [],
		"items": [],
		"safe": [],
		"safeAvailable": false
	}
}